abstractvoice/__init__.py
abstractvoice/__main__.py
abstractvoice/dependency_check.py
abstractvoice/instant_setup.py
abstractvoice/recognition.py
abstractvoice/simple_model_manager.py
abstractvoice/voice_manager.py
abstractvoice/examples/__init__.py
abstractvoice/examples/cli_repl.py
abstractvoice/examples/voice_cli.py
abstractvoice/examples/web_api.py
abstractvoice/stt/__init__.py
abstractvoice/stt/transcriber.py
abstractvoice/tts/__init__.py
abstractvoice/tts/tts_engine.py
abstractvoice/vad/__init__.py
abstractvoice/vad/voice_detector.py
abstractvoice-0.5.2.dist-info/licenses/LICENSE
abstractvoice-0.5.2.dist-info/METADATA
abstractvoice-0.5.2.dist-info/WHEEL
abstractvoice-0.5.2.dist-info/entry_points.txt
abstractvoice-0.5.2.dist-info/top_level.txt
abstractvoice-0.5.2.dist-info/RECORD
