Metadata-Version: 2.4
Name: abstractvoice
Version: 0.5.2
Summary: A modular Python library for voice interactions with AI systems
Author-email: Laurent-Philippe Albou <contact@abstractcore.ai>
License-Expression: MIT
Project-URL: Repository, https://github.com/lpalbou/abstractvoice
Project-URL: Documentation, https://github.com/lpalbou/abstractvoice#readme
Classifier: Development Status :: 3 - Alpha
Classifier: Intended Audience :: Developers
Classifier: Programming Language :: Python :: 3
Classifier: Programming Language :: Python :: 3.8
Classifier: Programming Language :: Python :: 3.9
Classifier: Programming Language :: Python :: 3.10
Classifier: Programming Language :: Python :: 3.11
Classifier: Programming Language :: Python :: 3.12
Requires-Python: >=3.8
License-File: LICENSE
Requires-Dist: numpy>=1.24.0
Requires-Dist: requests>=2.31.0
Requires-Dist: appdirs>=1.4.0
Requires-Dist: coqui-tts<0.30.0,>=0.27.0
Requires-Dist: torch<2.9.0,>=2.1.0
Requires-Dist: torchvision<1.0.0,>=0.16.0
Requires-Dist: torchaudio<2.9.0,>=2.1.0
Requires-Dist: librosa>=0.10.0
Requires-Dist: sounddevice>=0.4.6
Requires-Dist: soundfile>=0.12.1
Provides-Extra: voice
Requires-Dist: sounddevice>=0.4.6; extra == "voice"
Requires-Dist: webrtcvad>=2.0.10; extra == "voice"
Requires-Dist: PyAudio>=0.2.13; extra == "voice"
Requires-Dist: soundfile>=0.12.1; extra == "voice"
Provides-Extra: tts
Requires-Dist: coqui-tts<0.30.0,>=0.27.0; extra == "tts"
Requires-Dist: torch<2.9.0,>=2.1.0; extra == "tts"
Requires-Dist: torchvision<1.0.0,>=0.16.0; extra == "tts"
Requires-Dist: torchaudio<2.9.0,>=2.1.0; extra == "tts"
Requires-Dist: librosa>=0.10.0; extra == "tts"
Provides-Extra: stt
Requires-Dist: openai-whisper>=20230314; extra == "stt"
Requires-Dist: tiktoken>=0.6.0; extra == "stt"
Provides-Extra: web
Requires-Dist: flask>=2.0.0; extra == "web"
Provides-Extra: all
Requires-Dist: sounddevice>=0.4.6; extra == "all"
Requires-Dist: webrtcvad>=2.0.10; extra == "all"
Requires-Dist: PyAudio>=0.2.13; extra == "all"
Requires-Dist: openai-whisper>=20230314; extra == "all"
Requires-Dist: coqui-tts<0.30.0,>=0.27.0; extra == "all"
Requires-Dist: torch<2.9.0,>=2.1.0; extra == "all"
Requires-Dist: torchvision<1.0.0,>=0.16.0; extra == "all"
Requires-Dist: torchaudio<2.9.0,>=2.1.0; extra == "all"
Requires-Dist: librosa>=0.10.0; extra == "all"
Requires-Dist: soundfile>=0.12.1; extra == "all"
Requires-Dist: flask>=2.0.0; extra == "all"
Requires-Dist: tiktoken>=0.6.0; extra == "all"
Provides-Extra: dev
Requires-Dist: pytest>=7.0.0; extra == "dev"
Requires-Dist: black>=22.0.0; extra == "dev"
Requires-Dist: flake8>=5.0.0; extra == "dev"
Provides-Extra: voice-full
Requires-Dist: sounddevice>=0.4.6; extra == "voice-full"
Requires-Dist: webrtcvad>=2.0.10; extra == "voice-full"
Requires-Dist: PyAudio>=0.2.13; extra == "voice-full"
Requires-Dist: openai-whisper>=20230314; extra == "voice-full"
Requires-Dist: coqui-tts<0.30.0,>=0.27.0; extra == "voice-full"
Requires-Dist: torch<2.9.0,>=2.1.0; extra == "voice-full"
Requires-Dist: torchvision<1.0.0,>=0.16.0; extra == "voice-full"
Requires-Dist: torchaudio<2.9.0,>=2.1.0; extra == "voice-full"
Requires-Dist: librosa>=0.10.0; extra == "voice-full"
Requires-Dist: soundfile>=0.12.1; extra == "voice-full"
Requires-Dist: tiktoken>=0.6.0; extra == "voice-full"
Provides-Extra: core-tts
Requires-Dist: coqui-tts<0.30.0,>=0.27.0; extra == "core-tts"
Requires-Dist: torch<2.9.0,>=2.1.0; extra == "core-tts"
Requires-Dist: torchvision<1.0.0,>=0.16.0; extra == "core-tts"
Requires-Dist: torchaudio<2.9.0,>=2.1.0; extra == "core-tts"
Requires-Dist: librosa>=0.10.0; extra == "core-tts"
Provides-Extra: core-stt
Requires-Dist: openai-whisper>=20230314; extra == "core-stt"
Requires-Dist: tiktoken>=0.6.0; extra == "core-stt"
Provides-Extra: audio-only
Requires-Dist: sounddevice>=0.4.6; extra == "audio-only"
Requires-Dist: webrtcvad>=2.0.10; extra == "audio-only"
Requires-Dist: PyAudio>=0.2.13; extra == "audio-only"
Requires-Dist: soundfile>=0.12.1; extra == "audio-only"
Dynamic: license-file
